clipmake/__init__.py
clipmake/clipmake.py
clipmake-0.1.0.dist-info/LICENSE
clipmake-0.1.0.dist-info/METADATA
clipmake-0.1.0.dist-info/WHEEL
clipmake-0.1.0.dist-info/entry_points.txt
clipmake-0.1.0.dist-info/top_level.txt
clipmake-0.1.0.dist-info/RECORD
